alumath_matrixlib/__init__.py
alumath_matrixlib/matrix_operations.py
alumath_matrixlib-1.0.4.dist-info/METADATA
alumath_matrixlib-1.0.4.dist-info/WHEEL
alumath_matrixlib-1.0.4.dist-info/top_level.txt
alumath_matrixlib-1.0.4.dist-info/RECORD
