Metadata-Version: 2.4
Name: alumath-matrixlib
Version: 1.0.4
Summary: A simple matrix multiplication library made for a school project
Author-email: Hirwa Armstrong Brian <h.brian@alustudent.com>
Project-URL: Homepage, https://github.com/Pam-Pam29/ADVANCED-LINEAR-ALGEBRA-PCA-Group-19
Classifier: Programming Language :: Python :: 3
Classifier: License :: OSI Approved :: MIT License
Classifier: Operating System :: OS Independent
Requires-Python: >=3.6
